LICENSE.txt
MANIFEST.in
README.md
setup.py
bin/plotbr
bin/plotbrdiff
bin/printhist
bin/uidcommon
bin/uiddump
pyTuplingUtils/__init__.py
pyTuplingUtils/argparse.py
pyTuplingUtils/cutflow.py
pyTuplingUtils/io.py
pyTuplingUtils/plot.py
pyTuplingUtils/utils.py
pyTuplingUtils.egg-info/PKG-INFO
pyTuplingUtils.egg-info/SOURCES.txt
pyTuplingUtils.egg-info/dependency_links.txt
pyTuplingUtils.egg-info/requires.txt
pyTuplingUtils.egg-info/top_level.txt
pyTuplingUtils/boolean/__init__.py
pyTuplingUtils/boolean/const.py
pyTuplingUtils/boolean/eval.py
pyTuplingUtils/boolean/syntax.py
test/context.py
test/test_argparse.py
test/test_boolean_eval.py
test/test_boolean_syntax.py
test/test_cutflow.py
test/test_plot.py