Metadata-Version: 2.1
Name: pyTuplingUtils
Version: 0.3.3
Summary: Utilities for ntuples, such as plotting and simple debugging, with the help of uproot
Home-page: https://github.com/umd-lhcb/pyTuplingUtils
Author: Yipeng Sun
Author-email: syp@umd.edu
Classifier: Programming Language :: Python :: 3
Classifier: License :: OSI Approved :: BSD License
Classifier: Operating System :: OS Independent
License-File: LICENSE.txt
